Workbook

Sheet Sales_Data
A1: Order ID | B1: Order Date | C1: Country | D1: Sales Rep | E1: Product Category | F1: Product | G1: Units Sold | H1: Unit Price | I1: Discount % | J1: Channel | K1: Region | L1: Ageing(from order date) | M1: Gross Revenue | N1: Net Revenue | O1: Order Classification | P1: Priority Channel | Q1: Region
A2: 1001 | B2: 01-Jan-24 | C2: India | D2: Ayaan | E2: Laptop | F2: Dell Inspiron | G2: 3 | H2: 800 | I2: 5 | J2: Online | K2: ? | L2: =DATEDIF(B2,TODAY(),"Y")&" years "&DATEDIF(B2,TODAY(),"YM")&" months "&DATEDIF(B2,TODAY(),"MD")&" days" -> 2 years 2 months 16 days | M2: =G2*H2 -> 2400 | N2: =(100-I2)*0.01*M2 -> 2280 | O2: =IF(AND(N2>=3000,G2>=3),"High", IF(AND(N2>=1500,N2<=2999),"Medium", "Low")) -> Medium | P2: =IF(AND(J2="Online",N2>=2500),"High", IF(OR(J2="Retail",G2>=4),"Medium", "Low")) -> Low | Q2: =VLOOKUP(D2,Sheet1!A:B,2,FALSE) -> Asia
A3: 1002 | B3: 45293 | C3: USA | D3: Riya | E3: Phone | F3: iPhone 14 | G3: 2 | H3: 900 | I3: 3 | J3: Retail | K3: ? | L3: =DATEDIF(B3,TODAY(),"Y")&" years "&DATEDIF(B3,TODAY(),"YM")&" months "&DATEDIF(B3,TODAY(),"MD")&" days" -> 2 years 2 months 15 days | M3: =G3*H3 -> 1800 | N3: =(100-I3)*0.01*M3 -> 1746 | O3: =IF(AND(N3>=3000,G3>=3),"High", IF(AND(N3>=1500,N3<=2999),"Medium", "Low")) -> Medium | P3: =IF(AND(J3="Online",N3>=2500),"High", IF(OR(J3="Retail",G3>=4),"Medium", "Low")) -> Medium | Q3: =VLOOKUP(D3,Sheet1!A:B,2,FALSE) -> North America
A4: 1003 | B4: 02-Jan-24 | C4: India | D4: Kabir | E4: Tablet | F4: iPad Air | G4: 4 | H4: 600 | I4: 4 | J4: Online | K4: ? | L4: =DATEDIF(B4,TODAY(),"Y")&" years "&DATEDIF(B4,TODAY(),"YM")&" months "&DATEDIF(B4,TODAY(),"MD")&" days" -> 2 years 2 months 15 days | M4: =G4*H4 -> 2400 | N4: =(100-I4)*0.01*M4 -> 2304 | O4: =IF(AND(N4>=3000,G4>=3),"High", IF(AND(N4>=1500,N4<=2999),"Medium", "Low")) -> Medium | P4: =IF(AND(J4="Online",N4>=2500),"High", IF(OR(J4="Retail",G4>=4),"Medium", "Low")) -> Medium | Q4: =VLOOKUP(D4,Sheet1!A:B,2,FALSE) -> Asia
A5: 1004 | B5: 03-Jan-24 | C5: Germany | D5: Maya | E5: Laptop | F5: HP Pavilion | G5: 2 | H5: 750 | I5: 5 | J5: Retail | K5: ? | L5: =DATEDIF(B5,TODAY(),"Y")&" years "&DATEDIF(B5,TODAY(),"YM")&" months "&DATEDIF(B5,TODAY(),"MD")&" days" -> 2 years 2 months 14 days | M5: =G5*H5 -> 1500 | N5: =(100-I5)*0.01*M5 -> 1425 | O5: =IF(AND(N5>=3000,G5>=3),"High", IF(AND(N5>=1500,N5<=2999),"Medium", "Low")) -> Low | P5: =IF(AND(J5="Online",N5>=2500),"High", IF(OR(J5="Retail",G5>=4),"Medium", "Low")) -> Medium | Q5: =VLOOKUP(D5,Sheet1!A:B,2,FALSE) -> Europe
A6: 1005 | B6: 03-Jan-24 | C6: UK | D6: Sara | E6: Phone | F6: Samsung S23 | G6: 5 | H6: 850 | I6: 6 | J6: Online | K6: ? | L6: =DATEDIF(B6,TODAY(),"Y")&" years "&DATEDIF(B6,TODAY(),"YM")&" months "&DATEDIF(B6,TODAY(),"MD")&" days" -> 2 years 2 months 14 days | M6: =G6*H6 -> 4250 | N6: =(100-I6)*0.01*M6 -> 3995 | O6: =IF(AND(N6>=3000,G6>=3),"High", IF(AND(N6>=1500,N6<=2999),"Medium", "Low")) -> High | P6: =IF(AND(J6="Online",N6>=2500),"High", IF(OR(J6="Retail",G6>=4),"Medium", "Low")) -> High | Q6: =VLOOKUP(D6,Sheet1!A:B,2,FALSE) -> Europe
A7: 1006 | B7: 04-Jan-24 | C7: India | D7: Rohit | E7: Laptop | F7: MacBook Air | G7: 1 | H7: 1200 | I7: 2 | J7: Online | K7: ? | L7: =DATEDIF(B7,TODAY(),"Y")&" years "&DATEDIF(B7,TODAY(),"YM")&" months "&DATEDIF(B7,TODAY(),"MD")&" days" -> 2 years 2 months 13 days | M7: =G7*H7 -> 1200 | N7: =(100-I7)*0.01*M7 -> 1176 | O7: =IF(AND(N7>=3000,G7>=3),"High", IF(AND(N7>=1500,N7<=2999),"Medium", "Low")) -> Low | P7: =IF(AND(J7="Online",N7>=2500),"High", IF(OR(J7="Retail",G7>=4),"Medium", "Low")) -> Low | Q7: =VLOOKUP(D7,Sheet1!A:B,2,FALSE) -> Asia
A8: 1007 | B8: 04-Jan-24 | C8: USA | D8: Arjun | E8: Tablet | F8: Samsung Tab | G8: 3 | H8: 550 | I8: 4 | J8: Retail | K8: ? | L8: =DATEDIF(B8,TODAY(),"Y")&" years "&DATEDIF(B8,TODAY(),"YM")&" months "&DATEDIF(B8,TODAY(),"MD")&" days" -> 2 years 2 months 13 days | M8: =G8*H8 -> 1650 | N8: =(100-I8)*0.01*M8 -> 1584 | O8: =IF(AND(N8>=3000,G8>=3),"High", IF(AND(N8>=1500,N8<=2999),"Medium", "Low")) -> Medium | P8: =IF(AND(J8="Online",N8>=2500),"High", IF(OR(J8="Retail",G8>=4),"Medium", "Low")) -> Medium | Q8: =VLOOKUP(D8,Sheet1!A:B,2,FALSE) -> North America
A9: 1008 | B9: 05-Jan-24 | C9: India | D9: Isha | E9: Phone | F9: OnePlus 11 | G9: 6 | H9: 650 | I9: 5 | J9: Online | K9: ? | L9: =DATEDIF(B9,TODAY(),"Y")&" years "&DATEDIF(B9,TODAY(),"YM")&" months "&DATEDIF(B9,TODAY(),"MD")&" days" -> 2 years 2 months 12 days | M9: =G9*H9 -> 3900 | N9: =(100-I9)*0.01*M9 -> 3705 | O9: =IF(AND(N9>=3000,G9>=3),"High", IF(AND(N9>=1500,N9<=2999),"Medium", "Low")) -> High | P9: =IF(AND(J9="Online",N9>=2500),"High", IF(OR(J9="Retail",G9>=4),"Medium", "Low")) -> High | Q9: =VLOOKUP(D9,Sheet1!A:B,2,FALSE) -> Asia
A10: 1009 | B10: 06-Jan-24 | C10: Germany | D10: Kunal | E10: Laptop | F10: Lenovo ThinkPad | G10: 2 | H10: 950 | I10: 3 | J10: Retail | K10: ? | L10: =DATEDIF(B10,TODAY(),"Y")&" years "&DATEDIF(B10,TODAY(),"YM")&" months "&DATEDIF(B10,TODAY(),"MD")&" days" -> 2 years 2 months 11 days | M10: =G10*H10 -> 1900 | N10: =(100-I10)*0.01*M10 -> 1843 | O10: =IF(AND(N10>=3000,G10>=3),"High", IF(AND(N10>=1500,N10<=2999),"Medium", "Low")) -> Medium | P10: =IF(AND(J10="Online",N10>=2500),"High", IF(OR(J10="Retail",G10>=4),"Medium", "Low")) -> Medium | Q10: =VLOOKUP(D10,Sheet1!A:B,2,FALSE) -> #N/A
A11: 1010 | B11: 06-Jan-24 | C11: India | D11: Neha | E11: Tablet | F11: iPad Air | G11: 3 | H11: 600 | I11: 4 | J11: Online | K11: ? | L11: =DATEDIF(B11,TODAY(),"Y")&" years "&DATEDIF(B11,TODAY(),"YM")&" months "&DATEDIF(B11,TODAY(),"MD")&" days" -> 2 years 2 months 11 days | M11: =G11*H11 -> 1800 | N11: =(100-I11)*0.01*M11 -> 1728 | O11: =IF(AND(N11>=3000,G11>=3),"High", IF(AND(N11>=1500,N11<=2999),"Medium", "Low")) -> Medium | P11: =IF(AND(J11="Online",N11>=2500),"High", IF(OR(J11="Retail",G11>=4),"Medium", "Low")) -> Low | Q11: =VLOOKUP(D11,Sheet1!A:B,2,FALSE) -> Asia
A12: 1011 | B12: 07-Jan-24 | C12: UK | D12: Tia | E12: Laptop | F12: Dell Inspiron | G12: 4 | H12: 800 | I12: 5 | J12: Retail | K12: ? | L12: =DATEDIF(B12,TODAY(),"Y")&" years "&DATEDIF(B12,TODAY(),"YM")&" months "&DATEDIF(B12,TODAY(),"MD")&" days" -> 2 years 2 months 10 days | M12: =G12*H12 -> 3200 | N12: =(100-I12)*0.01*M12 -> 3040 | O12: =IF(AND(N12>=3000,G12>=3),"High", IF(AND(N12>=1500,N12<=2999),"Medium", "Low")) -> High | P12: =IF(AND(J12="Online",N12>=2500),"High", IF(OR(J12="Retail",G12>=4),"Medium", "Low")) -> Medium | Q12: =VLOOKUP(D12,Sheet1!A:B,2,FALSE) -> #N/A
A13: 1012 | B13: 07-Jan-24 | C13: USA | D13: Aryan | E13: Phone | F13: iPhone 14 | G13: 2 | H13: 900 | I13: 3 | J13: Online | K13: ? | L13: =DATEDIF(B13,TODAY(),"Y")&" years "&DATEDIF(B13,TODAY(),"YM")&" months "&DATEDIF(B13,TODAY(),"MD")&" days" -> 2 years 2 months 10 days | M13: =G13*H13 -> 1800 | N13: =(100-I13)*0.01*M13 -> 1746 | O13: =IF(AND(N13>=3000,G13>=3),"High", IF(AND(N13>=1500,N13<=2999),"Medium", "Low")) -> Medium | P13: =IF(AND(J13="Online",N13>=2500),"High", IF(OR(J13="Retail",G13>=4),"Medium", "Low")) -> Low | Q13: =VLOOKUP(D13,Sheet1!A:B,2,FALSE) -> #N/A
A14: 1013 | B14: 08-Jan-24 | C14: India | D14: Dev | E14: Phone | F14: Samsung S23 | G14: 3 | H14: 850 | I14: 6 | J14: Online | K14: ? | L14: =DATEDIF(B14,TODAY(),"Y")&" years "&DATEDIF(B14,TODAY(),"YM")&" months "&DATEDIF(B14,TODAY(),"MD")&" days" -> 2 years 2 months 9 days | M14: =G14*H14 -> 2550 | N14: =(100-I14)*0.01*M14 -> 2397 | O14: =IF(AND(N14>=3000,G14>=3),"High", IF(AND(N14>=1500,N14<=2999),"Medium", "Low")) -> Medium | P14: =IF(AND(J14="Online",N14>=2500),"High", IF(OR(J14="Retail",G14>=4),"Medium", "Low")) -> Low | Q14: =VLOOKUP(D14,Sheet1!A:B,2,FALSE) -> Asia
A15: 1014 | B15: 08-Jan-24 | C15: Germany | D15: Simran | E15: Laptop | F15: HP Pavilion | G15: 1 | H15: 750 | I15: 5 | J15: Retail | K15: ? | L15: =DATEDIF(B15,TODAY(),"Y")&" years "&DATEDIF(B15,TODAY(),"YM")&" months "&DATEDIF(B15,TODAY(),"MD")&" days" -> 2 years 2 months 9 days | M15: =G15*H15 -> 750 | N15: =(100-I15)*0.01*M15 -> 712.5 | O15: =IF(AND(N15>=3000,G15>=3),"High", IF(AND(N15>=1500,N15<=2999),"Medium", "Low")) -> Low | P15: =IF(AND(J15="Online",N15>=2500),"High", IF(OR(J15="Retail",G15>=4),"Medium", "Low")) -> Medium | Q15: =VLOOKUP(D15,Sheet1!A:B,2,FALSE) -> #N/A
... A31: 1030 | B31: 16-Jan-24 | C31: India | D31: Riya | E31: Tablet | F31: Samsung Tab | G31: 4 | H31: 550 | I31: 4 | J31: Online | K31: ? | L31: =DATEDIF(B31,TODAY(),"Y")&" years "&DATEDIF(B31,TODAY(),"YM")&" months "&DATEDIF(B31,TODAY(),"MD")&" days" -> 2 years 2 months 1 days | M31: =G31*H31 -> 2200 | N31: =(100-I31)*0.01*M31 -> 2112 | O31: =IF(AND(N31>=3000,G31>=3),"High", IF(AND(N31>=1500,N31<=2999),"Medium", "Low")) -> Medium | P31: =IF(AND(J31="Online",N31>=2500),"High", IF(OR(J31="Retail",G31>=4),"Medium", "Low")) -> Medium | Q31: =VLOOKUP(D31,Sheet1!A:B,2,FALSE) -> North America
K35: Total Revenue generated from India through Online Channel | O35: =SUMIFS(M:M,C:C,"India",J:J,"Online") -> 30750
J36: number of orders where Country is India AND Product Category is Laptop | O36: =COUNTIFS(C:C,"India",E:E,"Laptop") -> 4
L37: 3 highest Net Revenue orders | O37: =LARGE(N2:N31,1) -> 3995
O38: =LARGE(N2:N31,2) -> 3705
O39: =LARGE(N2:N31,3) -> 3196

Sheet Sheet1
A1: Product | B1: Product
A3: Sales Rep | B3: Region
A4: Ayaan | B4: Asia
A5: Riya | B5: North America
A6: Kabir | B6: Asia
A7: Maya | B7: Europe
A8: Sara | B8: Europe
A9: Rohit | B9: Asia
A10: Arjun | B10: North America
A11: Isha | B11: Asia
A12: Neha | B12: Asia
A13: Dev | B13: Asia

Sheet pivot_table
A3: Row Labels | B3: Sum of Gross Revenue
A4: Germany | B4: 10000
A5: India | B5: 30750
A6: UK | B6: 11750
A7: USA | B7: 10750
A8: Grand Total | B8: 63250
A11: Row Labels | B11: Sum of Units Sold
A12: Laptop | B12: 24
A13: Phone | B13: 32
A14: Tablet | B14: 30
A15: Grand Total | B15: 86
A18: Row Labels | B18: Sum of Gross Revenue
A19: Online | B19: 42200
A20: India | B20: 30750
A21: UK | B21: 6050
A22: USA | B22: 5400
A23: Retail | B23: 21050
A24: Germany | B24: 10000
A25: UK | B25: 5700
A26: USA | B26: 5350
A27: Grand Total | B27: 63250
